LICENSE
README.md
setup.cfg
setup.py
connectortestpython/__init__.py
connectortestpython/main.py
connectortestpython/passwork_api.py
connectortestpython/session_options.py
connectortestpython.egg-info/PKG-INFO
connectortestpython.egg-info/SOURCES.txt
connectortestpython.egg-info/dependency_links.txt
connectortestpython.egg-info/requires.txt
connectortestpython.egg-info/top_level.txt
connectortestpython/examples/__init__.py
connectortestpython/examples/add_password.py
connectortestpython/examples/delete_password.py
connectortestpython/examples/get_password.py
connectortestpython/examples/search_password.py
connectortestpython/rest_modules/__init__.py
connectortestpython/rest_modules/passwords.py
connectortestpython/rest_modules/users.py
connectortestpython/rest_modules/vaults.py
connectortestpython/utils/__init__.py
connectortestpython/utils/base32.py
connectortestpython/utils/crypto_file.py
connectortestpython/utils/crypto_interface.py
connectortestpython/utils/passwork_utils.py