Metadata-Version: 2.1
Name: connectortestpython
Version: 1.0.1
Summary: Test module
Home-page: https://github.com/dimavladimirov/mini_connector
Author: dimavladimirov
Author-email: vladimirovdmitry@mail.ru
Project-URL: Documentation, https:/www.google.com
Keywords: example python
Classifier: Programming Language :: Python :: 3.10
Classifier: License :: OSI Approved :: MIT License
Classifier: Operating System :: OS Independent
Requires-Python: >=3.10
License-File: LICENSE
